setup.py
AutoTestManager/__init__.py
AutoTestManager/client/__init__.py
AutoTestManager/client/ai_client.py
AutoTestManager/client/main.py
AutoTestManager/client/modules/__init__.py
AutoTestManager/client/modules/board_log.py
AutoTestManager/client/modules/detect.py
AutoTestManager/client/modules/ftp.py
AutoTestManager/client/modules/gerrit.py
AutoTestManager/client/modules/reboot.py
AutoTestManager/client/modules/redmine.py
AutoTestManager/client/modules/stream_x_press.py
AutoTestManager/client/modules/testlink.py
AutoTestManager/server/__init__.py
AutoTestManager/server/main.py
AutoTestManager/server/save_task.py
AutoTestManager/server/modules/__init__.py
AutoTestManager/server/modules/board_manager.py
AutoTestManager/server/modules/cmdclient.py
AutoTestManager/server/modules/ftp.py
AutoTestManager/server/modules/log.py
AutoTestManager/server/modules/msg.py
AutoTestManager/server/modules/queuelib.py
AutoTestManager/server/modules/sendmsg.py
AutoTestManager/server/modules/user.py
GxAutoTestManager.egg-info/PKG-INFO
GxAutoTestManager.egg-info/SOURCES.txt
GxAutoTestManager.egg-info/dependency_links.txt
GxAutoTestManager.egg-info/entry_points.txt
GxAutoTestManager.egg-info/requires.txt
GxAutoTestManager.egg-info/top_level.txt