Metadata-Version: 1.0
Name: GxAutoTestManager
Version: 1.0.0
Summary: pctools
Home-page: https://github.com/DancePerth/GxAutoTestManager
Author: DancePerth
Author-email: 28daysinperth@gmail.com
License: UNKNOWN
Platform: UNKNOWN
